{"stats":{"minecraft:killed":{"minecraft:zombified_piglin":1,"minecraft:spider":1,"minecraft:skeleton":9,"minecraft:chicken":6,"minecraft:piglin_brute":1,"minecraft:magma_cube":7,"minecraft:piglin":2,"minecraft:pig":9,"minecraft:sheep":5,"minecraft:zombie":6,"minecraft:cow":21,"iceandfire:fire_dragon":4,"minecraft:husk":2},"minecraft:broken":{"minecraft:stone_pickaxe":2,"minecraft:shield":1},"minecraft:picked_up":{"minecraft:wheat":20,"minecraft:anvil":2,"minecraft:nether_brick_fence":1,"doggytalents:koji":2,"celestisynth:solar_crystal_leggings":1,"artifacts:umbrella":1,"minecraft:lead":2,"minecraft:diamond_sword":4,"minecraft:oak_stairs":7,"farmersdelight:apple_pie_slice":3,"celestisynth:solar_crystal_helmet":1,"farmersdelight:cutting_board":1,"minecraft:string":8,"minecraft:soul_soil":5,"doggytalents:uncooked_rice":14,"minecraft:raw_copper":4,"celestisynth:solar_crystal_boots":1,"minecraft:pufferfish":2,"minecraft:oak_sign":1,"minecraft:beetroot":4,"minecraft:diamond_leggings":8,"mca:engagement_ring":1,"minecraft:gold_nugget":74,"minecraft:cobbled_deepslate":704,"minecraft:cobblestone_slab":6,"minecraft:netherite_upgrade_smithing_template":3,"minecraft:enchanted_golden_apple":1,"minecraft:melon_slice":3,"iceandfire:armor_bronze_boots":1,"minecraft:furnace":11,"minecraft:stick":84,"minecraft:oak_fence":8,"minecraft:torch":24,"minecraft:porkchop":15,"celestisynth:solar_crystal_chestplate":1,"iceandfire:armor_bronze_chestplate":2,"iceandfire:lightning_dragon_blood":3,"minecraft:diorite":92,"farmersdelight:chicken_cuts":6,"minecraft:golden_chestplate":1,"minecraft:brown_carpet":2,"minecraft:rotten_flesh":20,"minecraft:tropical_fish":1,"farmersdelight:onion":26,"iceandfire:fire_dragon_heart":1,"minecraft:iron_block":1,"iceandfire:armor_green_helmet":2,"minecraft:obsidian":24,"minecraft:cobblestone":781,"minecraft:feather":5,"minecraft:water_bucket":1,"minecraft:andesite":28,"farmersdelight:bacon":14,"minecraft:potato":2,"minecraft:flint":3,"minecraft:tuff":33,"farmersdelight:cooked_bacon":14,"minecraft:lapis_lazuli":5,"farmersdelight:tomato":6,"minecraft:dirt":187,"iceandfire:dragonscales_bronze":84,"minecraft:lantern":6,"farmersdelight:mutton_chops":4,"minecraft:bone":123,"farmersdelight:iron_knife":2,"minecraft:bow":2,"minecraft:wheat_seeds":140,"minecraft:mossy_stone_bricks":1,"minecraft:diamond_helmet":2,"minecraft:glowstone_dust":2,"minecraft:oak_planks":335,"iceandfire:dragon_skull_fire":11,"minecraft:sand":49,"cfm:oak_upgraded_fence":1,"minecraft:ink_sac":1,"farmersdelight:cooked_mutton_chops":5,"minecraft:mossy_cobblestone":1,"iceandfire:chared_cobblestone":1,"minecraft:diamond":90,"iceandfire:fire_dragon_blood":9,"minecraft:bone_meal":6,"minecraft:cracked_polished_blackstone_bricks":2,"minecraft:crossbow":1,"minecraft:granite":45,"minecraft:emerald":15,"minecraft:oak_sapling":6,"minecraft:netherrack":275,"iceandfire:silver_nugget":10,"iceandfire:raw_silver":3,"minecraft:diamond_pickaxe":4,"sophisticatedbackpacks:gold_backpack":1,"iceandfire:dragon_skull_lightning":1,"minecraft:charcoal":2,"minecraft:crafting_table":16,"minecraft:chicken":6,"minecraft:clay_ball":1,"minecraft:gold_block":1,"doggytalents:rice_wheat":46,"gravestone:obituary":43,"farmersdelight:diamond_knife":1,"minecraft:oak_trapdoor":6,"minecraft:iron_axe":3,"minecraft:item_frame":2,"minecraft:blackstone":1,"farmersdelight:beef_patty":11,"minecraft:candle":14,"minecraft:beef":53,"minecraft:oak_boat":1,"minecraft:light_gray_wool":2,"minecraft:sugar_cane":9,"minecraft:chest":10,"minecraft:egg":10,"minecraft:raw_iron":15,"minecraft:sandstone":4,"iceandfire:dragonbone":168,"iceandfire:dragonscales_green":23,"minecraft:oak_door":6,"farmersdelight:minced_beef":14,"minecraft:polished_blackstone_bricks":2,"farmersdelight:tomato_seeds":2,"minecraft:carrot":53,"minecraft:redstone":21,"minecraft:arrow":93,"minecraft:diamond_chestplate":3,"farmersdelight:cooked_chicken_cuts":6,"minecraft:beetroot_seeds":13,"celestisynth:solar_crystal":40,"minecraft:nether_bricks":34,"minecraft:diamond_boots":6,"minecraft:hay_block":3,"artifacts:running_shoes":2,"minecraft:gold_ingot":16,"sophisticatedbackpacks:copper_backpack":1,"minecraft:mutton":7,"minecraft:bone_block":9,"minecraft:rail":1,"minecraft:skeleton_skull":4,"minecraft:white_wool":2,"minecraft:air":0,"minecraft:leather":34,"minecraft:red_mushroom":1,"doggytalents:rice_grains":32,"minecraft:oak_log":36,"iceandfire:armor_bronze_leggings":1,"minecraft:ancient_debris":5,"minecraft:golden_boots":2,"minecraft:gunpowder":2,"mca:book_romance":3,"minecraft:stone_bricks":4,"farmersdelight:cooking_pot":1,"minecraft:kelp":3,"minecraft:iron_ingot":76,"minecraft:oak_fence_gate":1,"minecraft:stone_pickaxe":2,"minecraft:cooked_chicken":1,"iceandfire:fire_dragon_flesh":3,"iceandfire:chared_stone":7,"minecraft:scaffolding":2,"minecraft:pink_bed":1,"iceandfire:armor_bronze_helmet":1,"iceandfire:ash":1,"minecraft:quartz":19,"minecraft:dandelion":1,"minecraft:gravel":16,"minecraft:amethyst_shard":2,"minecraft:white_bed":11,"minecraft:crying_obsidian":2,"minecraft:spider_eye":2,"minecraft:diamond_shovel":2,"minecraft:stone_axe":1,"minecraft:diamond_axe":3,"minecraft:baked_potato":3,"minecraft:black_wool":1,"minecraft:coal":214},"minecraft:killed_by":{"iceandfire:cyclops":4,"siren_head:siren_head":1,"iceandfire:fire_dragon":21,"minecraft:player":9},"minecraft:custom":{"minecraft:animals_bred":24,"minecraft:interact_with_crafting_table":103,"minecraft:leave_game":11,"minecraft:time_since_death":13257,"minecraft:damage_resisted":2,"minecraft:sprint_one_cm":1435609,"minecraft:damage_blocked_by_shield":1100,"minecraft:drop":463,"minecraft:play_time":647528,"minecraft:deaths":65,"minecraft:jump":10608,"minecraft:walk_on_water_one_cm":69133,"minecraft:interact_with_furnace":77,"minecraft:sleep_in_bed":5,"minecraft:damage_dealt":17225,"minecraft:player_kills":2,"minecraft:crouch_one_cm":27140,"waystones:waystone_activated":4,"minecraft:horse_one_cm":1237,"minecraft:interact_with_anvil":1,"minecraft:mob_kills":76,"minecraft:interact_with_campfire":2,"minecraft:climb_one_cm":2656,"minecraft:walk_one_cm":1322490,"minecraft:sneak_time":14596,"minecraft:walk_under_water_one_cm":46798,"minecraft:boat_one_cm":251715,"minecraft:total_world_time":647528,"minecraft:time_since_rest":13290,"minecraft:damage_absorbed":2,"minecraft:damage_taken":21755,"minecraft:swim_one_cm":170163,"minecraft:fly_one_cm":2045797,"minecraft:open_chest":379,"minecraft:fall_one_cm":349535},"minecraft:dropped":{"iceandfire:chared_stone":7,"iceandfire:raw_silver":3,"minecraft:lapis_lazuli":5,"minecraft:candle":1,"minecraft:diamond_axe":2,"celestisynth:solar_crystal_chestplate":1,"minecraft:cooked_beef":7,"iceandfire:armor_bronze_helmet":3,"minecraft:glass_bottle":1,"minecraft:diamond":22,"minecraft:crafting_table":2,"minecraft:crossbow":1,"farmersdelight:cooked_bacon":2,"iceandfire:fire_dragon_flesh":3,"minecraft:lantern":6,"minecraft:leather":6,"minecraft:rail":1,"minecraft:red_mushroom":1,"minecraft:flint":3,"sophisticatedbackpacks:gold_backpack":1,"minecraft:emerald":7,"minecraft:gold_block":1,"minecraft:dirt":76,"minecraft:bone_meal":3,"gravestone:obituary":105,"minecraft:gold_nugget":69,"minecraft:amethyst_shard":4,"farmersdelight:cooked_mutton_chops":3,"minecraft:bone_block":1,"iceandfire:ash":1,"minecraft:polished_blackstone_bricks":1,"minecraft:sand":43,"iceandfire:fire_dragon_blood":2,"minecraft:iron_pickaxe":1,"minecraft:white_wool":2,"minecraft:bone":5,"minecraft:oak_door":6,"minecraft:gravel":12,"minecraft:stone_axe":1,"minecraft:blackstone":1,"minecraft:ancient_debris":1,"minecraft:cooked_chicken":1,"minecraft:cobbled_deepslate":599,"minecraft:wheat":1,"minecraft:obsidian":15,"minecraft:rotten_flesh":20,"minecraft:oak_planks":181,"minecraft:glowstone_dust":2,"doggytalents:rice_wheat":33,"minecraft:nether_brick_fence":1,"mca:engagement_ring":2,"farmersdelight:cooked_chicken_cuts":2,"minecraft:gunpowder":2,"minecraft:beetroot_seeds":3,"minecraft:leather_boots":1,"minecraft:chest":1,"minecraft:leather_leggings":1,"doggytalents:rice_grains":30,"minecraft:arrow":24,"minecraft:crying_obsidian":1,"minecraft:scaffolding":1,"minecraft:netherrack":44,"iceandfire:armor_bronze_leggings":1,"minecraft:egg":1,"minecraft:iron_ingot":4,"minecraft:golden_boots":1,"minecraft:wheat_seeds":143,"iceandfire:armor_green_leggings":1,"minecraft:mossy_cobblestone":1,"iceandfire:dragonscales_green":8,"minecraft:diamond_leggings":6,"minecraft:feather":5,"minecraft:cobblestone":352,"minecraft:granite":43,"celestisynth:solar_crystal_helmet":1,"minecraft:tropical_fish":1,"minecraft:stick":5,"minecraft:pufferfish":2,"minecraft:diorite":92,"minecraft:ink_sac":1,"minecraft:torch":22,"minecraft:diamond_helmet":1,"minecraft:oak_stairs":1,"minecraft:string":8,"minecraft:bucket":1,"farmersdelight:apple_pie_slice":2,"iceandfire:dragon_skull_fire":9,"iceandfire:dragonscales_bronze":15,"minecraft:dandelion":1,"iceandfire:silver_nugget":10,"minecraft:soul_soil":5,"minecraft:raw_copper":4,"minecraft:tuff":33,"minecraft:raw_iron":1,"minecraft:chicken":2,"celestisynth:solar_crystal_boots":1,"iceandfire:armor_bronze_boots":2,"minecraft:light_gray_wool":2,"celestisynth:solar_crystal_leggings":1,"minecraft:iron_hoe":2,"sophisticatedbackpacks:backpack":1,"iceandfire:armor_bronze_chestplate":2,"minecraft:nether_bricks":14,"minecraft:oak_sign":9,"minecraft:diamond_sword":1,"minecraft:potato":2,"minecraft:shield":1,"minecraft:diamond_chestplate":2,"iceandfire:chared_cobblestone":1,"minecraft:diamond_pickaxe":3,"minecraft:andesite":27,"minecraft:mossy_stone_bricks":1,"minecraft:oak_sapling":3,"minecraft:spider_eye":2,"minecraft:stone_bricks":3,"minecraft:brown_carpet":1,"minecraft:diamond_boots":3,"minecraft:sandstone":4,"iceandfire:fire_dragon_heart":1,"sophisticatedbackpacks:copper_backpack":2,"minecraft:bow":2,"minecraft:wooden_pickaxe":1,"minecraft:stone_pickaxe":4,"farmersdelight:tomato":1,"minecraft:black_wool":1},"minecraft:crafted":{"doggytalents:rice_bowl":8,"minecraft:oak_planks":56,"minecraft:oak_sign":9,"minecraft:cobblestone_slab":12,"celestisynth:solar_crystal_helmet":1,"minecraft:cooked_chicken":1,"minecraft:cooked_mutton":4,"minecraft:glass":6,"minecraft:diamond_helmet":1,"minecraft:diamond_leggings":3,"iceandfire:armor_green_helmet":1,"minecraft:chest":4,"minecraft:golden_boots":1,"minecraft:glass_bottle":6,"minecraft:oak_slab":12,"minecraft:item_frame":2,"minecraft:cooked_porkchop":5,"minecraft:diamond_axe":1,"minecraft:crafting_table":4,"farmersdelight:iron_knife":2,"minecraft:baked_potato":4,"minecraft:wooden_pickaxe":1,"minecraft:campfire":5,"farmersdelight:cutting_board":3,"minecraft:diamond_pickaxe":2,"minecraft:shield":1,"minecraft:stick":76,"minecraft:iron_ingot":19,"minecraft:iron_pickaxe":1,"minecraft:gold_ingot":3,"iceandfire:armor_bronze_helmet":2,"celestisynth:solar_crystal_leggings":1,"minecraft:coal":54,"iceandfire:armor_green_leggings":1,"minecraft:leather_leggings":1,"minecraft:leather_boots":1,"minecraft:furnace":5,"celestisynth:solar_crystal_boots":1,"minecraft:bone_meal":6,"farmersdelight:pie_crust":2,"minecraft:oak_trapdoor":2,"minecraft:iron_axe":1,"minecraft:iron_hoe":1,"minecraft:stone_pickaxe":5,"minecraft:diamond_boots":2,"iceandfire:armor_bronze_chestplate":3,"minecraft:wheat":27,"minecraft:cooked_beef":41,"minecraft:sugar":5,"farmersdelight:apple_pie":2,"minecraft:diamond_sword":1,"mca:engagement_ring":1,"iceandfire:armor_bronze_boots":3,"minecraft:dried_kelp":64,"celestisynth:solar_crystal_chestplate":1,"minecraft:bowl":256,"minecraft:bucket":1,"minecraft:stone_axe":1,"minecraft:jungle_slab":6,"minecraft:air":0,"minecraft:oak_boat":2,"minecraft:oak_stairs":4,"cfm:oak_upgraded_fence":12,"farmersdelight:diamond_knife":1,"iceandfire:armor_bronze_leggings":2,"minecraft:torch":8,"minecraft:diamond_chestplate":1},"minecraft:used":{"minecraft:oak_sign":1,"minecraft:chest":11,"minecraft:shield":64,"doggytalents:rice_grains":19,"celestisynth:solar_crystal_chestplate":2,"minecraft:mutton":1,"artifacts:umbrella":60,"minecraft:nether_bricks":16,"minecraft:carrot":52,"minecraft:obsidian":11,"farmersdelight:tomato":2,"minecraft:stone_bricks":1,"minecraft:item_frame":4,"minecraft:brown_carpet":1,"minecraft:bow":2,"farmersdelight:cutting_board":4,"minecraft:scaffolding":1,"minecraft:furnace":13,"minecraft:beetroot_seeds":7,"minecraft:skeleton_skull":1,"minecraft:egg":9,"minecraft:golden_boots":1,"iceandfire:armor_bronze_boots":1,"minecraft:leather_leggings":1,"minecraft:oak_planks":34,"minecraft:stone_pickaxe":273,"celestisynth:solar_crystal_helmet":2,"iceandfire:armor_green_helmet":1,"minecraft:sugar_cane":4,"minecraft:diamond_axe":203,"celestisynth:solar_crystal_leggings":1,"farmersdelight:apple_pie_slice":1,"minecraft:crying_obsidian":1,"minecraft:melon_slice":3,"cfm:oak_upgraded_fence":11,"minecraft:diamond_sword":290,"minecraft:fire_charge":1,"iceandfire:dragon_skull_fire":1,"minecraft:andesite":1,"minecraft:oak_boat":2,"minecraft:bone_meal":9,"minecraft:oak_trapdoor":7,"celestisynth:solar_crystal_boots":2,"minecraft:flint_and_steel":2,"minecraft:redstone":1,"minecraft:cooked_chicken":1,"minecraft:netherrack":152,"minecraft:torch":6,"minecraft:dirt":79,"minecraft:anvil":2,"minecraft:golden_chestplate":1,"minecraft:granite":2,"minecraft:oak_fence_gate":1,"farmersdelight:beef_patty":8,"minecraft:iron_hoe":125,"minecraft:iron_axe":1,"minecraft:oak_stairs":26,"iceandfire:armor_bronze_leggings":1,"minecraft:beef":10,"farmersdelight:cooking_pot":1,"farmersdelight:cooked_mutton_chops":1,"minecraft:cooked_beef":34,"farmersdelight:tomato_seeds":2,"minecraft:cobbled_deepslate":198,"minecraft:enchanted_golden_apple":1,"minecraft:wheat_seeds":14,"minecraft:cooked_mutton":4,"minecraft:water_bucket":3,"minecraft:baked_potato":4,"minecraft:cobblestone_slab":18,"iceandfire:dragon_skull_lightning":1,"minecraft:leather_boots":1,"minecraft:polished_blackstone_bricks":1,"farmersdelight:onion":10,"minecraft:oak_slab":12,"minecraft:crafting_table":18,"minecraft:white_bed":10,"minecraft:campfire":3,"farmersdelight:apple_pie":2,"minecraft:oak_log":1,"minecraft:diamond_pickaxe":1636,"minecraft:apple":2,"minecraft:diamond_shovel":45,"minecraft:cracked_polished_blackstone_bricks":2,"minecraft:iron_pickaxe":188,"minecraft:stone_axe":53,"minecraft:pink_bed":1,"farmersdelight:cooked_bacon":12,"minecraft:cobblestone":161,"minecraft:cooked_porkchop":5,"minecraft:bucket":2,"minecraft:candle":13},"minecraft:mined":{"minecraft:white_bed":10,"minecraft:pink_bed":2,"iceandfire:copper_pile":2,"minecraft:obsidian":8,"minecraft:granite":52,"minecraft:grass_block":80,"minecraft:cracked_polished_blackstone_bricks":19,"minecraft:spawner":1,"minecraft:polished_blackstone_bricks":14,"minecraft:tall_seagrass":2,"minecraft:iron_ore":10,"minecraft:cobbled_deepslate":4,"minecraft:fire":41,"minecraft:anvil":2,"minecraft:oak_stairs":6,"iceandfire:gold_pile":4,"minecraft:dirt_path":1,"minecraft:blackstone":2,"minecraft:melon":1,"minecraft:chest":2,"minecraft:dead_bush":1,"minecraft:nether_quartz_ore":22,"minecraft:cobblestone":26,"minecraft:sugar_cane":5,"minecraft:oak_planks":10,"minecraft:wall_torch":1,"minecraft:skeleton_skull":1,"minecraft:seagrass":1,"minecraft:wheat":24,"farmersdelight:cutting_board":1,"celestisynth:solar_crystal":3,"minecraft:grass":85,"minecraft:oak_log":36,"minecraft:beetroots":4,"minecraft:oak_fence_gate":1,"minecraft:sand":6,"minecraft:dirt":74,"minecraft:netherrack":203,"minecraft:oak_leaves":1,"minecraft:deepslate":534,"iceandfire:chared_stone":4,"minecraft:diamond_ore":3,"minecraft:crying_obsidian":1,"minecraft:tuff":18,"farmersdelight:onions":6,"iceandfire:silver_ore":3,"minecraft:mossy_cobblestone":1,"minecraft:deepslate_diamond_ore":74,"minecraft:candle":8,"minecraft:nether_bricks":29,"gravestone:gravestone":56,"minecraft:redstone_wire":1,"farmersdelight:tomatoes":2,"minecraft:red_mushroom":1,"minecraft:hay_block":3,"minecraft:oak_trapdoor":7,"minecraft:furnace":8,"minecraft:carrots":15,"minecraft:andesite":17,"cfm:oak_upgraded_fence":2,"minecraft:nether_brick_fence":1,"minecraft:cobblestone_slab":5,"minecraft:bone_block":9,"minecraft:stone":831,"doggytalents:rice_crop":18,"minecraft:glass_pane":2,"minecraft:basalt":4,"minecraft:oak_fence":9,"minecraft:crafting_table":15,"minecraft:emerald_ore":6,"minecraft:campfire":1,"minecraft:tall_grass":19,"minecraft:diorite":47,"iceandfire:ash":1,"iceandfire:silver_pile":3,"minecraft:coal_ore":71,"minecraft:gravel":11,"minecraft:stone_bricks":4,"minecraft:fern":1}},"DataVersion":3465}